<?xml version="1.0" encoding="UTF-8"?>
<!DOCTYPE suite SYSTEM "https://testng.org/testng-1.0.dtd">
<suite name="Suite">
	<test thread-count="5" name="Test">
		<classes>
			<class name="com.crm.Sdet.Campaign.CreateCampaign">
				<methods>
					<include name="createcampaign"></include>
				</methods>
			</class>
			<class name="com.crm.Sdet.Campaign.CreateCampaignWithProduct">
				<methods>
					<include name="createcampaignwithproduct"></include>
				</methods>
			</class>

			<class
				name="com.crm.Sdet.Campaign.CreateCampaignWithProductAndDeleteProduct">
				<methods>
					<include name="createcampaignwithproductanddelete"></include>
				</methods>
			</class>
		</classes>
	</test> <!-- Test -->
</suite> <!-- Suite -->
